openworld/sdk/core/__init__.py
openworld/sdk/core/client/__init__.py
openworld/sdk/core/client/api.py
openworld/sdk/core/client/auth_client.py
openworld/sdk/core/client/openworld_auth_client.py
openworld/sdk/core/client/rapid_auth_client.py
openworld/sdk/core/configuration/__init__.py
openworld/sdk/core/configuration/auth_config.py
openworld/sdk/core/configuration/client_config.py
openworld/sdk/core/constant/__init__.py
openworld/sdk/core/constant/body.py
openworld/sdk/core/constant/constant.py
openworld/sdk/core/constant/header.py
openworld/sdk/core/constant/log.py
openworld/sdk/core/constant/message.py
openworld/sdk/core/constant/url.py
openworld/sdk/core/model/__init__.py
openworld/sdk/core/model/authentication.py
openworld/sdk/core/model/error.py
openworld/sdk/core/model/rapid_auth.py
openworld/sdk/core/model/exception/client.py
openworld/sdk/core/model/exception/openworld.py
openworld/sdk/core/model/exception/service.py
openworld/sdk/core/util/__init__.py
openworld/sdk/core/util/log.py
openworld_sdk_python_core-0.10.0.dist-info/METADATA
openworld_sdk_python_core-0.10.0.dist-info/WHEEL
openworld_sdk_python_core-0.10.0.dist-info/top_level.txt
openworld_sdk_python_core-0.10.0.dist-info/RECORD
